README.md
setup.py
pylha/__init__.py
pylha/export.py
pylha/parse.py
pylha.egg-info/PKG-INFO
pylha.egg-info/PKG-INFO.sync-conflict-20171102-080619-BNBPC44
pylha.egg-info/SOURCES.sync-conflict-20171102-080533-BNBPC44.txt
pylha.egg-info/SOURCES.txt
pylha.egg-info/dependency_links.txt
pylha.egg-info/requires.txt
pylha.egg-info/top_level.txt
pylha/tests/data/SPheno-2.spc.MSSM
pylha/tests/data/SPheno.spc
pylha/tests/data/SPheno.spc.MSSM
pylha/tests/data/isajet.txt
pylha/tests/data/isasusy.spc
pylha/tests/data/sdecay.bin
pylha/tests/data/slha.txt
pylha/tests/data/softsusy.spc
pylha/tests/data/sps1a.spc