Metadata-Version: 1.0
Name: pylha
Version: 0.3
Summary: A Python package to convert data files in SLHA and similar formats to Python objects, JSON, or YAML.
Home-page: https://github.com/DavidMStraub/pylha
Author: David M. Straub
Author-email: david.straub@tum.de
License: MIT
Platform: UNKNOWN
